mcp_server_ida/__init__.py
mcp_server_ida/__main__.py
mcp_server_ida/server.py
mcp_server_ida-0.3.4.dist-info/METADATA
mcp_server_ida-0.3.4.dist-info/WHEEL
mcp_server_ida-0.3.4.dist-info/entry_points.txt
mcp_server_ida-0.3.4.dist-info/licenses/LICENSE
mcp_server_ida-0.3.4.dist-info/RECORD
