Metadata-Version: 2.4
Name: mcp-server-ida
Version: 0.3.4
Summary: A Model Context Protocol server providing tools to read, search IDA Database programmatically via LLMs
Author: Mx-Iris
License: MIT
License-File: LICENSE
Keywords: automation,ida,llm,mcp
Classifier: Development Status :: 4 - Beta
Classifier: Intended Audience :: Developers
Classifier: License :: OSI Approved :: MIT License
Classifier: Programming Language :: Python :: 3
Classifier: Programming Language :: Python :: 3.10
Requires-Python: >=3.10
Requires-Dist: click>=8.1.7
Requires-Dist: mcp>=1.0.0
Requires-Dist: pydantic>=2.0.0
